rdt/__init__.py
rdt/_utils.py
rdt/errors.py
rdt/hyper_transformer.py
rdt/performance/__init__.py
rdt/performance/performance.py
rdt/performance/profiling.py
rdt/performance/datasets/__init__.py
rdt/performance/datasets/base.py
rdt/performance/datasets/boolean.py
rdt/performance/datasets/categorical.py
rdt/performance/datasets/datetime.py
rdt/performance/datasets/id.py
rdt/performance/datasets/numerical.py
rdt/performance/datasets/pii.py
rdt/performance/datasets/text.py
rdt/performance/datasets/utils.py
rdt/transformers/__init__.py
rdt/transformers/_validators.py
rdt/transformers/base.py
rdt/transformers/boolean.py
rdt/transformers/categorical.py
rdt/transformers/datetime.py
rdt/transformers/id.py
rdt/transformers/null.py
rdt/transformers/numerical.py
rdt/transformers/text.py
rdt/transformers/utils.py
rdt/transformers/pii/__init__.py
rdt/transformers/pii/anonymization.py
rdt/transformers/pii/anonymizer.py
rdt/transformers/pii/utils.py
rdt-1.20.0.dist-info/licenses/LICENSE
rdt-1.20.0.dist-info/METADATA
rdt-1.20.0.dist-info/WHEEL
rdt-1.20.0.dist-info/entry_points.txt
rdt-1.20.0.dist-info/top_level.txt
rdt-1.20.0.dist-info/RECORD
