Metadata-Version: 2.4
Name: rdt
Version: 1.20.0
Summary: Reversible Data Transforms
Author-email: "DataCebo, Inc." <info@sdv.dev>
License: BSL-1.1
Project-URL: Source Code, https://github.com/sdv-dev/RDT/
Project-URL: Issue Tracker, https://github.com/sdv-dev/RDT/issues
Project-URL: Changes, https://github.com/sdv-dev/RDT/blob/main/HISTORY.md
Project-URL: Twitter, https://twitter.com/sdv_dev
Project-URL: Chat, https://bit.ly/sdv-slack-invite
Keywords: machine learning,synthetic data generation,benchmark,generative models
Classifier: Development Status :: 5 - Production/Stable
Classifier: Intended Audience :: Developers
Classifier: License :: Free for non-commercial use
Classifier: Natural Language :: English
Classifier: Programming Language :: Python :: 3
Classifier: Programming Language :: Python :: 3.9
Classifier: Programming Language :: Python :: 3.10
Classifier: Programming Language :: Python :: 3.11
Classifier: Programming Language :: Python :: 3.12
Classifier: Programming Language :: Python :: 3.13
Classifier: Programming Language :: Python :: 3.14
Classifier: Topic :: Scientific/Engineering :: Artificial Intelligence
Requires-Python: <3.15,>=3.9
License-File: LICENSE
Requires-Dist: numpy>=1.21.0; python_version < "3.10"
Requires-Dist: numpy>=1.23.3; python_version >= "3.10" and python_version < "3.12"
Requires-Dist: numpy>=1.26.0; python_version >= "3.12" and python_version < "3.13"
Requires-Dist: numpy>=2.1.0; python_version >= "3.13" and python_version < "3.14"
Requires-Dist: numpy>=2.3.2; python_version >= "3.14"
Requires-Dist: pandas<3,>=1.4.0; python_version < "3.11"
Requires-Dist: pandas<3,>=1.5.0; python_version >= "3.11" and python_version < "3.12"
Requires-Dist: pandas<3,>=2.1.1; python_version >= "3.12" and python_version < "3.13"
Requires-Dist: pandas<3,>=2.2.3; python_version >= "3.13" and python_version < "3.14"
Requires-Dist: pandas<3,>=2.3.3; python_version >= "3.14"
Requires-Dist: scipy>=1.7.3; python_version < "3.10"
Requires-Dist: scipy>=1.9.2; python_version >= "3.10" and python_version < "3.12"
Requires-Dist: scipy>=1.12.0; python_version >= "3.12" and python_version < "3.13"
Requires-Dist: scipy>=1.14.1; python_version >= "3.13" and python_version < "3.14"
Requires-Dist: scipy>=1.16.1; python_version >= "3.14"
Requires-Dist: scikit-learn>=1.0.2; python_version < "3.10"
Requires-Dist: scikit-learn>=1.1.0; python_version >= "3.10" and python_version < "3.11"
Requires-Dist: scikit-learn>=1.1.3; python_version >= "3.11" and python_version < "3.12"
Requires-Dist: scikit-learn>=1.3.1; python_version >= "3.12" and python_version < "3.13"
Requires-Dist: scikit-learn>=1.5.2; python_version >= "3.13" and python_version < "3.14"
Requires-Dist: scikit-learn>=1.8.0; python_version >= "3.14"
Requires-Dist: Faker!=37.11.0,>=17
Requires-Dist: python-dateutil>=2.9
Provides-Extra: copulas
Requires-Dist: copulas>=0.12.1; python_version < "3.14" and extra == "copulas"
Requires-Dist: copulas>=0.14.0; python_version >= "3.14" and extra == "copulas"
Provides-Extra: pyarrow
Requires-Dist: pyarrow>=17.0.0; extra == "pyarrow"
Provides-Extra: test
Requires-Dist: rdt[pyarrow]; extra == "test"
Requires-Dist: rdt[copulas]; extra == "test"
Requires-Dist: pytest>=3.4.2; extra == "test"
Requires-Dist: pytest-cov>=2.6.0; extra == "test"
Requires-Dist: jupyter<2,>=1.0.0; extra == "test"
Requires-Dist: pytest-subtests<1.0,>=0.5; extra == "test"
Requires-Dist: pytest-runner>=2.11.1; extra == "test"
Requires-Dist: tomli<3,>=2.0.0; extra == "test"
Provides-Extra: dev
Requires-Dist: rdt[test]; extra == "dev"
Requires-Dist: build<2,>=1.0.0; extra == "dev"
Requires-Dist: bump-my-version>=0.18.3; extra == "dev"
Requires-Dist: pip>=9.0.1; extra == "dev"
Requires-Dist: watchdog<5,>=1.0.1; extra == "dev"
Requires-Dist: ruff<1,>=0.3.2; extra == "dev"
Requires-Dist: twine>=1.10.0; extra == "dev"
Requires-Dist: wheel>=0.30.0; extra == "dev"
Requires-Dist: coverage<8,>=4.5.12; extra == "dev"
Requires-Dist: tabulate<1,>=0.8.9; extra == "dev"
Requires-Dist: invoke; extra == "dev"
Provides-Extra: readme
Requires-Dist: rundoc<0.5,>=0.4.3; extra == "readme"
Dynamic: license-file
